<?xml version = '1.0' encoding = 'UTF-8'?>
<TableProxyOraclev11g class="oracle.dbtools.crest.model.design.storage.oracle.v11g.TableProxyOraclev11g" name="detalleventa" directorySegmentName="seg_0" id="7F9CD1E5-B8FB-95DF-5F78-7F0AB941CE5F">
<createdBy>baggr</createdBy>
<createdTime>2021-10-07 16:21:39 UTC</createdTime>
<ownerDesignName>DM MR MASTERBIKE</ownerDesignName>
<logging>YES</logging>
<partitionedRowMovement>DISABLE</partitionedRowMovement>
<temporaryChanged>false</temporaryChanged>
<accessDriverType>oracle_loader</accessDriverType>
<rejectLimit></rejectLimit>
<columnProxies itemClass="oracle.dbtools.crest.model.design.storage.oracle.v12c.ColumnProxyOraclev12c">
<ColumnProxy name="id_producto" id="12088640-6F51-1FF2-3150-90A717CAF70C">
<createdBy>baggr</createdBy>
<createdTime>2021-10-07 16:21:39 UTC</createdTime>
<ownerDesignName>DM MR MASTERBIKE</ownerDesignName>
</ColumnProxy>
<ColumnProxy name="id_venta" id="4278BD41-EB3B-B270-5116-B02B3D62F0CB">
<createdBy>baggr</createdBy>
<createdTime>2021-10-07 16:21:39 UTC</createdTime>
<ownerDesignName>DM MR MASTERBIKE</ownerDesignName>
</ColumnProxy>
<ColumnProxy name="id_detalleventa" id="60BCCED6-CFA4-5BAC-E266-B48B11965F1E">
<createdBy>baggr</createdBy>
<createdTime>2021-10-07 16:21:39 UTC</createdTime>
<ownerDesignName>DM MR MASTERBIKE</ownerDesignName>
</ColumnProxy>
<ColumnProxy name="precioventa" id="CFA8F518-20CE-3812-3284-F34D3CA9A01F">
<createdBy>baggr</createdBy>
<createdTime>2021-10-07 16:21:39 UTC</createdTime>
<ownerDesignName>DM MR MASTERBIKE</ownerDesignName>
</ColumnProxy>
<ColumnProxy name="cantidad" id="FF586B18-C163-D405-B2D6-0AEACBB4D8A3">
<createdBy>baggr</createdBy>
<createdTime>2021-10-07 16:21:39 UTC</createdTime>
<ownerDesignName>DM MR MASTERBIKE</ownerDesignName>
</ColumnProxy>
</columnProxies>
<foreignKeys>
<ForeignKey class="oracle.dbtools.crest.model.design.storage.oracle.v10g.FKProxyOraclev10g" name="fk_detalleventa_venta" id="3AC1EB99-2BE6-9DCC-F418-BE7D91614EC0">
<createdBy>baggr</createdBy>
<createdTime>2021-10-07 16:21:39 UTC</createdTime>
<ownerDesignName>DM MR MASTERBIKE</ownerDesignName>
</ForeignKey>
<ForeignKey class="oracle.dbtools.crest.model.design.storage.oracle.v10g.FKProxyOraclev10g" name="fk_detalleventa_producto" id="A71232E5-9A1A-1BAE-085C-E8BCBEE842D8">
<createdBy>baggr</createdBy>
<createdTime>2021-10-07 16:21:39 UTC</createdTime>
<ownerDesignName>DM MR MASTERBIKE</ownerDesignName>
</ForeignKey>
</foreignKeys>
<primaryKeys>
<PrimaryKey class="oracle.dbtools.crest.model.design.storage.oracle.v10g.PKProxyOraclev10g" name="detalleventa_pk" id="41BF6968-4182-6703-9AAB-79F47C612FFE">
<createdBy>baggr</createdBy>
<createdTime>2021-10-07 16:21:39 UTC</createdTime>
<ownerDesignName>DM MR MASTERBIKE</ownerDesignName>
<indexSort>SORTED</indexSort>
</PrimaryKey>
</primaryKeys>
</TableProxyOraclev11g>